README.rst
setup.cfg
setup.py
ghelint/__init__.py
ghelint.egg-info/PKG-INFO
ghelint.egg-info/SOURCES.txt
ghelint.egg-info/dependency_links.txt
ghelint.egg-info/entry_points.txt
ghelint.egg-info/top_level.txt