Metadata-Version: 1.0
Name: ghelint
Version: 0.1
Summary: ghelint
Home-page: UNKNOWN
Author: UNKNOWN
Author-email: UNKNOWN
License: MIT
Platform: UNKNOWN
